README.txt
setup.py
src/gocept/__init__.py
src/gocept.sortfiles.egg-info/PKG-INFO
src/gocept.sortfiles.egg-info/SOURCES.txt
src/gocept.sortfiles.egg-info/dependency_links.txt
src/gocept.sortfiles.egg-info/entry_points.txt
src/gocept.sortfiles.egg-info/namespace_packages.txt
src/gocept.sortfiles.egg-info/not-zip-safe
src/gocept.sortfiles.egg-info/requires.txt
src/gocept.sortfiles.egg-info/top_level.txt
src/gocept/sortfiles/__init__.py
src/gocept/sortfiles/main.py
src/gocept/sortfiles/tests/__init__.py
src/gocept/sortfiles/tests/test_sort.py