Metadata-Version: 1.0
Name: gocept.sortfiles
Version: 1.0
Summary: A small utility that sorts all files in a directory into subdirectories
